AUTHORS.rst
CONTRIBUTING.rst
HISTORY.rst
LICENSE
MANIFEST.in
README.md
pyproject.toml
setup.cfg
src/UFalcon/__init__.py
src/UFalcon/bessel.py
src/UFalcon/constants.py
src/UFalcon/construct_maps.py
src/UFalcon/probe_weights.py
src/UFalcon/sbt_class.py
src/UFalcon/shells.py
src/UFalcon/utils.py
src/UFalcon.egg-info/PKG-INFO
src/UFalcon.egg-info/SOURCES.txt
src/UFalcon.egg-info/dependency_links.txt
src/UFalcon.egg-info/not-zip-safe
src/UFalcon.egg-info/requires.txt
src/UFalcon.egg-info/top_level.txt
tests/test_contruct_maps.py
tests/test_probe_weights.py
tests/test_shells.py
tests/test_utils.py