Metadata-Version: 2.1
Name: UFalcon
Version: 2.0.0
Summary: A package to construct full-sky signal maps from N-Body simulation output.
Author: Alexander Reeves
Author-email: areeves@phys.ethz.ch
License: MIT License
Project-URL: Source, https://cosmo-docs.phys.ethz.ch/UFalcon
Classifier: Intended Audience :: Science/Research
Classifier: Intended Audience :: Developers
Classifier: License :: OSI Approved :: MIT License
Classifier: Natural Language :: English
Classifier: Programming Language :: Python :: 3
Classifier: Programming Language :: Python :: 3.9
Classifier: Programming Language :: Python :: 3.10
Classifier: Operating System :: OS Independent
Requires-Python: >=3.8
Provides-Extra: dev
Provides-Extra: docs
License-File: LICENSE
License-File: AUTHORS.rst
